setup.py
on_http/__init__.py
on_http/api_client.py
on_http/configuration.py
on_http/rest.py
on_http.egg-info/PKG-INFO
on_http.egg-info/SOURCES.txt
on_http.egg-info/dependency_links.txt
on_http.egg-info/requires.txt
on_http.egg-info/top_level.txt
on_http/apis/__init__.py
on_http/apis/catalogs_api.py
on_http/apis/config_api.py
on_http/apis/files_api.py
on_http/apis/lookups_api.py
on_http/apis/nodes_api.py
on_http/apis/obms_api.py
on_http/apis/pollers_api.py
on_http/apis/profiles_api.py
on_http/apis/schemas_api.py
on_http/apis/skus_api.py
on_http/apis/templates_api.py
on_http/apis/versions_api.py
on_http/apis/workflow_tasks_api.py
on_http/apis/workflows_api.py
on_http/models/__init__.py
on_http/models/catalog_get.py
on_http/models/lookup_delete.py
on_http/models/lookup_get.py
on_http/models/lookup_patch.py
on_http/models/lookups_post.py
on_http/models/node_catalogs_get.py
on_http/models/node_catalogs_get_latest_source.py
on_http/models/node_delete.py
on_http/models/node_dhcp_whitelist_delete.py
on_http/models/node_dhcp_whitelist_post.py
on_http/models/node_get.py
on_http/models/node_obm_get.py
on_http/models/node_obm_identify_post.py
on_http/models/node_obm_post.py
on_http/models/node_patch.py
on_http/models/node_pollers_get.py
on_http/models/node_workflows_active_delete.py
on_http/models/node_workflows_active_get.py
on_http/models/node_workflows_get.py
on_http/models/node_workflows_post.py
on_http/models/nodes_post.py
on_http/models/obms_library_service_get.py
on_http/models/poller_delete.py
on_http/models/poller_get.py
on_http/models/poller_get_data.py
on_http/models/poller_get_data_current.py
on_http/models/pollers_library_service_get.py
on_http/models/pollers_pause.py
on_http/models/pollers_resume.py
on_http/models/pollers_update.py
on_http/models/profile_library_service_get.py
on_http/models/profile_library_service_put.py
on_http/models/schema_get.py
on_http/models/sku_delete.py
on_http/models/sku_delete_pack.py
on_http/models/sku_get.py
on_http/models/sku_get_nodes.py
on_http/models/sku_pack_id_put.py
on_http/models/sku_patch.py
on_http/models/template_library_service_get.py
on_http/models/workflow_get.py
