Metadata-Version: 1.0
Name: on-http
Version: 1.0.2
Summary: RackHD API Documentation
Home-page: UNKNOWN
Author: UNKNOWN
Author-email: UNKNOWN
License: UNKNOWN
Keywords: Swagger,RackHD API Documentation
Platform: UNKNOWN
